{
  "courses": [
    {
      "Course Code": "CA1023",
      "Course Name": "Introduction to Karnatic Music",
      "Semester": 4,
      "Credits": 1.0,
      "Registration Type": "Regular",
      "Course Type": "Creative Arts",
      "Segment": "5-6",
      "Instructor Name": "Dr. Haripriya Narasimhan",
      "Grade": "",
      "Feedback Status": ""
    },
    {
      "Course Code": "CA1042",
      "Course Name": "Western Classical Music through Bach, Beethoven and Brahms",
      "Semester": 4,
      "Credits": 1.0,
      "Registration Type": "Regular",
      "Course Type": "Creative Arts",
      "Segment": "1-2",
      "Instructor Name": "Dr. Haripriya Narasimhan",
      "Grade": "",
      "Feedback Status": ""
    },
    {
      "Course Code": "EE1204",
      "Course Name": "Engineering Electromagnetics",
      "Semester": 4,
      "Credits": 2.0,
      "Registration Type": "Regular",
      "Course Type": "Departmental Core Theory",
      "Segment": "3-6",
      "Instructor Name": "Dr. Naresh Kumar Emani",
      "Grade": "",
      "Feedback Status": ""
    },
    {
      "Course Code": "EE2200",
      "Course Name": "Electrical Machines",
      "Semester": 4,
      "Credits": 3.0,
      "Registration Type": "Regular",
      "Course Type": "Departmental Core Theory",
      "Segment": "1-6",
      "Instructor Name": "Dr. Yemula Pradeep Kumar",
      "Grade": "",
      "Feedback Status": ""
    },
    {
      "Course Code": "EE2400",
      "Course Name": "Analog Electronics",
      "Semester": 4,
      "Credits": 3.0,
      "Registration Type": "Regular",
      "Course Type": "Departmental Core Theory",
      "Segment": "1-6",
      "Instructor Name": "Dr. Abhishek Kumar",
      "Grade": "",
      "Feedback Status": ""
    },
    {
      "Course Code": "EE2401",
      "Course Name": "Analog Lab",
      "Semester": 4,
      "Credits": 2.0,
      "Registration Type": "Regular",
      "Course Type": "Departmental Core Laboratory",
      "Segment": "1-6",
      "Instructor Name": "Dr. Abhishek Kumar",
      "Grade": "",
      "Feedback Status": ""
    },
    {
      "Course Code": "EE2600",
      "Course Name": "Power System Analysis",
      "Semester": 4,
      "Credits": 3.0,
      "Registration Type": "Regular",
      "Course Type": "Departmental Core Theory",
      "Segment": "1-6",
      "Instructor Name": "Dr. Vaskar Sarkar",
      "Grade": "",
      "Feedback Status": ""
    },
    {
      "Course Code": "EE2800",
      "Course Name": "DSP",
      "Semester": 4,
      "Credits": 3.0,
      "Registration Type": "Regular",
      "Course Type": "Departmental Core Theory",
      "Segment": "1-6",
      "Instructor Name": "Dr. Lakshmi Prasad N",
      "Grade": "",
      "Feedback Status": ""
    },
    {
      "Course Code": "EM3020",
      "Course Name": "Introduction to Entrepreneurship",
      "Semester": 4,
      "Credits": 1.0,
      "Registration Type": "Regular",
      "Course Type": "Liberal Arts Elective",
      "Segment": "1-2",
      "Instructor Name": "Dr. M P Ganesh",
      "Grade": "",
      "Feedback Status": ""
    },
    {
      "Course Code": "EP4130",
      "Course Name": "Data Science Analysis",
      "Semester": 4,
      "Credits": 2.0,
      "Registration Type": "Regular",
      "Course Type": "Additional",
      "Segment": "1-4",
      "Instructor Name": "Dr. Shantanu Desai",
      "Grade": "",
      "Feedback Status": ""
    },
    {
      "Course Code": "LA1150",
      "Course Name": "Cultures of the world",
      "Semester": 4,
      "Credits": 1.0,
      "Registration Type": "Regular",
      "Course Type": "Liberal Arts Elective",
      "Segment": "3-4",
      "Instructor Name": "Dr. Haripriya Narasimhan",
      "Grade": "",
      "Feedback Status": ""
    },
    {
      "Course Code": "LA1730",
      "Course Name": "Anthropology and Media",
      "Semester": 4,
      "Credits": 1.0,
      "Registration Type": "Regular",
      "Course Type": "Liberal Arts Elective",
      "Segment": "1-2",
      "Instructor Name": "Dr. Haripriya Narasimhan",
      "Grade": "",
      "Feedback Status": ""
    },
    {
      "Course Code": "CS3550",
      "Course Name": "DBMS I",
      "Semester": 3,
      "Credits": 1.0,
      "Registration Type": "Regular",
      "Course Type": "Basic Engineering Skills",
      "Segment": "5-6",
      "Instructor Name": "Dr. Manohar Kaul",
      "Grade": "A+",
      "Feedback Status": "Feedback Submitted"
    },
    {
      "Course Code": "EE2100",
      "Course Name": "Matrix Theory",
      "Semester": 3,
      "Credits": 3.0,
      "Registration Type": "Regular",
      "Course Type": "Departmental Core Theory",
      "Segment": "1-6",
      "Instructor Name": "Dr. Aditya T Siripuram.",
      "Grade": "A",
      "Feedback Status": "Feedback Submitted"
    },
    {
      "Course Code": "EE2101",
      "Course Name": "Control Systems",
      "Semester": 3,
      "Credits": 3.0,
      "Registration Type": "Regular",
      "Course Type": "Departmental Core Theory",
      "Segment": "1-6",
      "Instructor Name": "Dr. Siva Rama Krishna Vanjari",
      "Grade": "B",
      "Feedback Status": "Feedback Submitted"
    },
    {
      "Course Code": "EE2102",
      "Course Name": "Probability and Random Processes",
      "Semester": 3,
      "Credits": 3.0,
      "Registration Type": "Regular",
      "Course Type": "Departmental Core Theory",
      "Segment": "1-6",
      "Instructor Name": "Dr. Abhinav Kumar",
      "Grade": "A",
      "Feedback Status": "Feedback Submitted"
    },
    {
      "Course Code": "EE2104",
      "Course Name": "Semiconductor Device Fundamentals",
      "Semester": 3,
      "Credits": 3.0,
      "Registration Type": "Regular",
      "Course Type": "Departmental Core Theory",
      "Segment": "1-6",
      "Instructor Name": "Dr. Sushmee Badhulika",
      "Grade": "B",
      "Feedback Status": "Feedback Submitted"
    },
    {
      "Course Code": "EE2301",
      "Course Name": "Electronic Devices and Circuits Lab",
      "Semester": 3,
      "Credits": 2.0,
      "Registration Type": "Regular",
      "Course Type": "Departmental Core Laboratory",
      "Segment": "1-6",
      "Instructor Name": "Dr. Oves Mohammed Hussein Badami",
      "Grade": "A",
      "Feedback Status": "Feedback Submitted"
    },
    {
      "Course Code": "LA1770",
      "Course Name": "Personality Development",
      "Semester": 3,
      "Credits": 1.0,
      "Registration Type": "Regular",
      "Course Type": "Liberal Arts Elective",
      "Segment": "1-2",
      "Instructor Name": "Dr. M P Ganesh",
      "Grade": "A",
      "Feedback Status": "Feedback Submitted"
    },
    {
      "Course Code": "BT1010",
      "Course Name": "Introduction to Life Sciences",
      "Semester": 2,
      "Credits": 1.0,
      "Registration Type": "Regular",
      "Course Type": "Basic Sciences",
      "Segment": "1-2",
      "Instructor Name": "Dr. Anindya Roy",
      "Grade": "A",
      "Feedback Status": "Feedback Submitted"
    },
    {
      "Course Code": "EE1102",
      "Course Name": "Basic Electrical Engineering",
      "Semester": 2,
      "Credits": 3.0,
      "Registration Type": "Regular",
      "Course Type": "Departmental Core Theory",
      "Segment": "1-6",
      "Instructor Name": "Dr. Yemula Pradeep Kumar",
      "Grade": "A",
      "Feedback Status": "Feedback Submitted"
    },
    {
      "Course Code": "EE1200",
      "Course Name": "Electrical Circuits Lab",
      "Semester": 2,
      "Credits": 2.0,
      "Registration Type": "Regular",
      "Course Type": "Departmental Core Laboratory",
      "Segment": "1-6",
      "Instructor Name": "Dr. Gajendranath Chaudhury",
      "Grade": "A",
      "Feedback Status": "Feedback Submitted"
    },
    {
      "Course Code": "EE1201",
      "Course Name": "Digital Systems",
      "Semester": 2,
      "Credits": 3.0,
      "Registration Type": "Regular",
      "Course Type": "Departmental Core Theory",
      "Segment": "1-6",
      "Instructor Name": "Dr. Siva Rama Krishna Vanjari",
      "Grade": "A-",
      "Feedback Status": "Feedback Submitted"
    },
    {
      "Course Code": "EE1203",
      "Course Name": "Vector Calculus",
      "Semester": 2,
      "Credits": 1.0,
      "Registration Type": "Regular",
      "Course Type": "Basic Sciences",
      "Segment": "3-4",
      "Instructor Name": "Dr. Sundaram Vanka",
      "Grade": "B",
      "Feedback Status": "Feedback Submitted"
    },
    {
      "Course Code": "EE1205",
      "Course Name": "Signals and Systems",
      "Semester": 2,
      "Credits": 3.0,
      "Registration Type": "Regular",
      "Course Type": "Departmental Core Theory",
      "Segment": "1-6",
      "Instructor Name": "Dr. Abhinav Kumar",
      "Grade": "A",
      "Feedback Status": "Feedback Submitted"
    },
    {
      "Course Code": "ID1050",
      "Course Name": "Artificial Intelligence",
      "Semester": 2,
      "Credits": 1.0,
      "Registration Type": "Regular",
      "Course Type": "Basic Engineering Skills",
      "Segment": "1-2",
      "Instructor Name": "Dr. Srijith P K",
      "Grade": "B",
      "Feedback Status": "Feedback Submitted"
    },
    {
      "Course Code": "ID1054",
      "Course Name": "Digital Fabrication",
      "Semester": 2,
      "Credits": 2.0,
      "Registration Type": "Regular",
      "Course Type": "Basic Engineering Skills",
      "Segment": "1-6",
      "Instructor Name": "Dr. Prasad S Onkar",
      "Grade": "A",
      "Feedback Status": "Feedback Submitted"
    },
    {
      "Course Code": "MA1150",
      "Course Name": "Differential Equations",
      "Semester": 2,
      "Credits": 1.0,
      "Registration Type": "Regular",
      "Course Type": "Basic Sciences",
      "Segment": "3-4",
      "Instructor Name": "Dr. Lakshmi Narayana P A",
      "Grade": "A",
      "Feedback Status": "Feedback Submitted"
    },
    {
      "Course Code": "MA2130",
      "Course Name": "Complex Variables",
      "Semester": 2,
      "Credits": 1.0,
      "Registration Type": "Regular",
      "Course Type": "Basic Sciences",
      "Segment": "1-2",
      "Instructor Name": "Dr. Tanmoy Paul",
      "Grade": "A-",
      "Feedback Status": "Feedback Submitted"
    },
    {
      "Course Code": "CY1018",
      "Course Name": "Environmental Chemistry Theory",
      "Semester": 1,
      "Credits": 2.0,
      "Registration Type": "Regular",
      "Course Type": "Basic Sciences",
      "Segment": "1-4",
      "Instructor Name": "Dr. Krishna Gavvala",
      "Grade": "A-",
      "Feedback Status": "Feedback Submitted"
    },
    {
      "Course Code": "EP1108",
      "Course Name": "Modern Physics",
      "Semester": 1,
      "Credits": 2.0,
      "Registration Type": "Regular",
      "Course Type": "Basic Sciences",
      "Segment": "3-6",
      "Instructor Name": "Dr. Shantanu Desai",
      "Grade": "B",
      "Feedback Status": "Feedback Submitted"
    },
    {
      "Course Code": "ID1063",
      "Course Name": "Introduction to Programming",
      "Semester": 1,
      "Credits": 3.0,
      "Registration Type": "Regular",
      "Course Type": "Basic Engineering Skills",
      "Segment": "1-6",
      "Instructor Name": "Dr. Saurabh Bhanuprasad Joshi",
      "Grade": "A-",
      "Feedback Status": "Feedback Submitted"
    },
    {
      "Course Code": "LA1760",
      "Course Name": "Communication Skills",
      "Semester": 1,
      "Credits": 2.0,
      "Registration Type": "Regular",
      "Course Type": "Liberal Arts Elective",
      "Segment": "3-6",
      "Instructor Name": "Dr. Nandini Ramesh Sankar",
      "Grade": "A-",
      "Feedback Status": "Feedback Submitted"
    },
    {
      "Course Code": "MA1110",
      "Course Name": "Calculus-I",
      "Semester": 1,
      "Credits": 1.0,
      "Registration Type": "Regular",
      "Course Type": "Basic Sciences",
      "Segment": "1-2",
      "Instructor Name": "Dr. Dipankar Ghosh",
      "Grade": "A",
      "Feedback Status": "Feedback Submitted"
    },
    {
      "Course Code": "MA1220",
      "Course Name": "Calculus-II",
      "Semester": 1,
      "Credits": 1.0,
      "Registration Type": "Regular",
      "Course Type": "Basic Sciences",
      "Segment": "3-4",
      "Instructor Name": "Dr. Mrinmoy Datta",
      "Grade": "A",
      "Feedback Status": "Feedback Submitted"
    },
    {
      "Course Code": "ME1020",
      "Course Name": "Engineering Mechanics",
      "Semester": 1,
      "Credits": 3.0,
      "Registration Type": "Regular",
      "Course Type": "Departmental Core Theory",
      "Segment": "1-6",
      "Instructor Name": "Dr. Viswanath Chinthapenta",
      "Grade": "A+",
      "Feedback Status": "Feedback Submitted"
    },
    {
      "Course Code": "ME1040",
      "Course Name": "Introduction to Artificial Intelligence",
      "Semester": 1,
      "Credits": 1.0,
      "Registration Type": "Regular",
      "Course Type": "Departmental Core Theory",
      "Segment": "4-6",
      "Instructor Name": "Dr. R.Prasanth Kumar",
      "Grade": "A",
      "Feedback Status": "Feedback Submitted"
    },
    {
      "Course Code": "NS1001",
      "Course Name": "National Sports Organization",
      "Semester": 1,
      "Credits": 0.0,
      "Registration Type": "Regular",
      "Course Type": "Additional",
      "Segment": "1-6",
      "Instructor Name": "Dr. Asif Qureshi",
      "Grade": "",
      "Feedback Status": "Feedback Not Submitted"
    },
    {
      "Course Code": "NS1002",
      "Course Name": "National Service Scheme",
      "Semester": 1,
      "Credits": 0.0,
      "Registration Type": "Regular",
      "Course Type": "Additional",
      "Segment": "1-6",
      "Instructor Name": "Dr. Digvijay S Pawar",
      "Grade": "",
      "Feedback Status": "Feedback Not Submitted"
    }
  ]
}